understory/icu.c
understory/kv.py
understory/sql.py
understory_db-0.0.8.dist-info/LICENSE
understory_db-0.0.8.dist-info/WHEEL
understory_db-0.0.8.dist-info/METADATA
understory_db-0.0.8.dist-info/RECORD
