Metadata-Version: 2.1
Name: understory-db
Version: 0.0.8
Summary: Tools for metamodern data management
License: AGPL-3.0-or-later
Author: Angelo Gladding
Author-email: angelo@lahacker.net
Requires-Python: >=3.7,<4.0
Classifier: License :: OSI Approved :: GNU Affero General Public License v3 or later (AGPLv3+)
Classifier: Programming Language :: Python :: 3
Classifier: Programming Language :: Python :: 3.7
Classifier: Programming Language :: Python :: 3.8
Classifier: Programming Language :: Python :: 3.9
Requires-Dist: pendulum (>=2.1.2,<3.0.0)
Requires-Dist: redis (>=3.5.3,<4.0.0)
Requires-Dist: sh (>=1.14.2,<2.0.0)
Requires-Dist: understory-fx (>=0.0.5,<0.0.6)
Project-URL: Homepage, https://github.com/canopy/understory-db
